[
    {
        "Title": "NH├ђ PHр╗љ NGр╗їC L├ѓM, LONG BI├іN, 17M x 5 Tр║дNG, GI├Ђ CHр╗ѕ C├Њ 3 Tр╗Х",
        "Description": "3 PN Рђб Nh├а ng├х, hр║╗m",
        "Price": "3 tр╗и",
        "Price per m┬▓": "176 tr/m┬▓",
        "Space": "17 m┬▓",
        "Location": "Quр║Гn Long Bi├фn Рђб h├┤m qua"
    },
    {
        "Title": "Gia ─љ├гnh em muр╗Љn b├Аn mр║Бnh ─Љр║Цt nghр╗Ѕ dк░р╗Аng view hр╗Њ",
        "Description": "─љр║Цt thр╗Ћ cк░ Рђб Ngang 10 m",
        "Price": "3 tр╗и",
        "Price per m┬▓": "176 tr/m┬▓",
        "Space": "17 m┬▓",
        "Location": "Huyр╗Єn Quр╗Љc Oai Рђб h├┤m qua"
    },
    {
        "Title": "B├Аn nh├а ─љр╗Іnh C├┤ng Hр║А, Ho├аng Mai 34m* 4tр║Дng gр║Дn ├┤ t├┤ ─Љр╗Ќ, gр║Дn phр╗Љ",
        "Description": "4 PN Рђб Nh├а ng├х, hр║╗m",
        "Price": "3 tр╗и",
        "Price per m┬▓": "176 tr/m┬▓",
        "Space": "17 m┬▓",
        "Location": "Quр║Гn Ho├аng Mai Рђб h├┤m qua"
    },
    {
        "Title": "B├Аn ─Љр║Цt chк░a sр╗Ћ Th├┤n ─љр║Аi Lan- Duy├фn H├а -Thanh Tr├г - H├а Nр╗Ўi.",
        "Description": "─љр║Цt thр╗Ћ cк░ Рђб Ngang 6 m",
        "Price": "3 tр╗и",
        "Price per m┬▓": "176 tr/m┬▓",
        "Space": "17 m┬▓",
        "Location": "Huyр╗Єn Thanh Tr├г Рђб h├┤m qua"
    },
    {
        "Title": "Ch├Гnh Chр╗Д Cр║Дn B├Аn Gр║Цp T├▓a Nh├а V─Ѓn Ph├▓ng Phр╗Љ Nguyр╗Ёn Ho├аng",
        "Description": "Mр║иt bр║▒ng kinh doanh",
        "Price": "3 tр╗и",
        "Price per m┬▓": "176 tr/m┬▓",
        "Space": "17 m┬▓",
        "Location": "Quр║Гn Nam Tр╗Ф Li├фm Рђб h├┤m qua"
    },
    {
        "Title": "B├Аn ─Љр║Цt Y├фn Ngh─Еa- H├а ─љ├┤ng- 62m- ng├х ├┤ t├┤- gр║Дn v├аnh ─Љai 4- x├бy CCMN cр╗▒",
        "Description": "─љр║Цt thр╗Ћ cк░",
        "Price": "3 tр╗и",
        "Price per m┬▓": "176 tr/m┬▓",
        "Space": "17 m┬▓",
        "Location": "Quр║Гn H├а ─љ├┤ng Рђб h├┤m qua"
    },
    {
        "Title": "Hр║А Gi├А - B├Аn Gр║Цp c─Ѓn hр╗Ў 82m2, 3PN Full NT chung cк░Licogi13 Tower",
        "Description": "3 PN Рђб Chung cк░",
        "Price": "3 tр╗и",
        "Price per m┬▓": "176 tr/m┬▓",
        "Space": "17 m┬▓",
        "Location": "Quр║Гn Thanh Xu├бn Рђб h├┤m qua"
    },
    {
        "Title": "HO├ђNG MAI, 46m * 5 Tр║дNG MT QUYр╗ђN Lр╗░C, ├ћT├ћ - Sр╗ћ ─љр╗ј RI├іNG ─љр║ИP",
        "Description": "4 PN Рђб Nh├а ng├х, hр║╗m",
        "Price": "3 tр╗и",
        "Price per m┬▓": "176 tr/m┬▓",
        "Space": "17 m┬▓",
        "Location": "Quр║Гn Ho├аng Mai Рђб h├┤m qua"
    },
    {
        "Title": "Mр║ХT PHр╗љ T─ѓNG THIр║ЙT GI├ЂP - ├ћT├ћ TR├ЂNH - KD -V─ѓN PH├њNG -Vр╗і TR├Ї ─љр║ИP",
        "Description": "5 PN Рђб Nh├а mр║иt phр╗Љ, mр║иt tiр╗Ђn",
        "Price": "3 tр╗и",
        "Price per m┬▓": "176 tr/m┬▓",
        "Space": "17 m┬▓",
        "Location": "Quр║Гn Bр║»c Tр╗Ф Li├фm Рђб h├┤m qua"
    },
    {
        "Title": "SI├іU PHр║еM Cр╗ћ NHUр║Й - H├ђNG ─љр║ИP- р╗ъ LU├ћN- Sр╗ћ VU├ћNG Vр║«N- 39M X 6,8 Tр╗Х ­Ъўё",
        "Description": "3 PN Рђб Nh├а ng├х, hр║╗m",
        "Price": "3 tр╗и",
        "Price per m┬▓": "176 tr/m┬▓",
        "Space": "17 m┬▓",
        "Location": "Quр║Гn Bр║»c Tр╗Ф Li├фm Рђб h├┤m qua"
    },
    {
        "Title": "NH├ђ р╗ъ CH├ЇNH TRUNG,TR├ѓU QUр╗▓,DT 102M2 CHAOG 10.5 Tр╗Х C├њN TL",
        "Description": "─љр║Цt thр╗Ћ cк░ Рђб Ngang 4 m",
        "Price": "3 tр╗и",
        "Price per m┬▓": "176 tr/m┬▓",
        "Space": "17 m┬▓",
        "Location": "Huyр╗Єn Gia L├бm Рђб h├┤m qua"
    },
    {
        "Title": "B├ЂN NH├ђ Cр╗ћ NHUр║Й - PH├ѓN L├ћ - ├ћ T├ћ ─љр╗ќ Cр╗гA - KINH DOANH - 55M X 13,9 Tр╗Х",
        "Description": "6 PN Рђб Nh├а ng├х, hр║╗m",
        "Price": "3 tр╗и",
        "Price per m┬▓": "176 tr/m┬▓",
        "Space": "17 m┬▓",
        "Location": "Quр║Гn Bр║»c Tр╗Ф Li├фm Рђб h├┤m qua"
    },
    {
        "Title": "B├ЂN NH├ђ Cр║дU GIр║цY - Gр║дN PHр╗љ - NG├Ћ TH├ћNG- BAGAC ─љр╗ќ Cр╗гA - 32M -6.350 Tр╗Х",
        "Description": "4 PN Рђб Nh├а ng├х, hр║╗m",
        "Price": "3 tр╗и",
        "Price per m┬▓": "176 tr/m┬▓",
        "Space": "17 m┬▓",
        "Location": "Quр║Гn Cр║Дu Giр║Цy Рђб h├┤m qua"
    },
    {
        "Title": "Mр║ХT PHр╗љ GI├ЂP NHр║цT 11 tр╗и",
        "Description": "3 PN Рђб Nh├а mр║иt phр╗Љ, mр║иt tiр╗Ђn",
        "Price": "3 tр╗и",
        "Price per m┬▓": "176 tr/m┬▓",
        "Space": "17 m┬▓",
        "Location": "Quр║Гn Thanh Xu├бn Рђб h├┤m qua"
    },
    {
        "Title": "B├Аn nh├а Phр╗Љ Kim Giang, 27m* 4tр║Дng, gр║Дn ├┤ t├┤ ─Љр╗Ќ, H├аng x├│m K─љT Linh ─љ├аm",
        "Description": "3 PN Рђб Nh├а ng├х, hр║╗m",
        "Price": "3 tр╗и",
        "Price per m┬▓": "176 tr/m┬▓",
        "Space": "17 m┬▓",
        "Location": "Quр║Гn Ho├аng Mai Рђб h├┤m qua"
    },
    {
        "Title": "H├ђNG Cр╗░C N├ЊNG - PV─љ- NGOр║аI GIAO ─љO├ђN - L├ћ Gр╗љC- ├ћT├ћ ─љр╗ќ Cр╗гA",
        "Description": "4 PN Рђб Nh├а mр║иt phр╗Љ, mр║иt tiр╗Ђn",
        "Price": "3 tр╗и",
        "Price per m┬▓": "176 tr/m┬▓",
        "Space": "17 m┬▓",
        "Location": "Quр║Гn Bр║»c Tр╗Ф Li├фm Рђб h├┤m qua"
    },
    {
        "Title": "B├Аn nh├а 4 tр║Дng gр║Дn 40m2 р╗дy Ban huyр╗Єn Thanh Tr├г gр║Дn CHр╗ѕ 5.x tр╗и",
        "Description": "4 PN Рђб Nh├а ng├х, hр║╗m",
        "Price": "3 tр╗и",
        "Price per m┬▓": "176 tr/m┬▓",
        "Space": "17 m┬▓",
        "Location": "Huyр╗Єn Thanh Tr├г Рђб h├┤m qua"
    },
    {
        "Title": "Mр║ХT PHр╗љ QUANG TRUNG H├ђ ─љ├ћNG, 37M, 5T, MT3,2M, GI├Ђ 12,8 Tр╗Х",
        "Description": "3 PN Рђб Nh├а mр║иt phр╗Љ, mр║иt tiр╗Ђn",
        "Price": "3 tр╗и",
        "Price per m┬▓": "176 tr/m┬▓",
        "Space": "17 m┬▓",
        "Location": "Quр║Гn H├а ─љ├┤ng Рђб h├┤m qua"
    },
    {
        "Title": "Cр║дN TIр╗ђN - B├ЂN Gр║цP NH├ђ THUр╗┤ PHк»каNG-L├ћ G├ЊC -├ћTO-S├ЂT PHр╗љ- 45MX 6,2 Tр╗Х",
        "Description": "4 PN Рђб Nh├а ng├х, hр║╗m",
        "Price": "3 tр╗и",
        "Price per m┬▓": "176 tr/m┬▓",
        "Space": "17 m┬▓",
        "Location": "Quр║Гn Bр║»c Tр╗Ф Li├фm Рђб h├┤m qua"
    },
    {
        "Title": "NH├ђ Cр║дU ─љка 5 H├ђ ─љ├ћNG, 39M, 5T, MT4,5M, 10,5 Tр╗Х",
        "Description": "3 PN Рђб Nh├а ng├х, hр║╗m",
        "Price": "3 tр╗и",
        "Price per m┬▓": "176 tr/m┬▓",
        "Space": "17 m┬▓",
        "Location": "Quр║Гn H├а ─љ├┤ng Рђб h├┤m qua"
    }
]